MANIFEST.in
README.rst
setup.py
plone/__init__.py
plone.app.texttile.egg-info/PKG-INFO
plone.app.texttile.egg-info/SOURCES.txt
plone.app.texttile.egg-info/dependency_links.txt
plone.app.texttile.egg-info/entry_points.txt
plone.app.texttile.egg-info/namespace_packages.txt
plone.app.texttile.egg-info/not-zip-safe
plone.app.texttile.egg-info/requires.txt
plone.app.texttile.egg-info/top_level.txt
plone/app/__init__.py
plone/app/texttile/__init__.py
plone/app/texttile/configure.zcml
plone/app/texttile/tile.css
plone/app/texttile/tile.js
plone/app/texttile/tile.png
plone/app/texttile/tile.pt
plone/app/texttile/tile.py
plone/app/texttile/tile.txt
plone/app/texttile/profiles/default/cssregistry.xml
plone/app/texttile/profiles/default/jsregistry.xml
plone/app/texttile/profiles/default/metadata.xml
plone/app/texttile/profiles/default/registry.xml
plone/app/texttile/tests/__init__.py
plone/app/texttile/tests/base.py
plone/app/texttile/tests/test_doctests.py