Metadata-Version: 1.0
Name: plone.app.texttile
Version: 1.0
Summary: Text tile for Deco UI
Home-page: https://github.com/plone/plone.app.texttile
Author: Rok Garbas
Author-email: rok@garbas.si
License: GPL
Keywords: plone deco tile
Platform: UNKNOWN
Classifier: Framework :: Plone
Classifier: Programming Language :: Python
Classifier: Topic :: Software Development :: Libraries :: Python Modules
